{"cameraMode":{"drawMode":0,"name":"Shaded","section":"Shading Mode"},"sceneLighting":true,"audioPlay":false,"sceneViewState":{"m_AlwaysRefresh":false,"showFog":true,"showSkybox":false,"showFlares":true,"showImageEffects":true,"showParticleSystems":true,"showVisualEffectGraphs":true,"m_FxEnabled":true},"in2DMode":false,"pivot":{"x":-5.649030685424805,"y":4.192570686340332,"z":14.578531265258789},"rotation":{"x":-0.13794465363025666,"y":-0.7660949230194092,"z":0.1753566712141037,"w":-0.6027972102165222},"size":8.932689666748047,"orthographic":false}